maginator/__init__.py
maginator/controller.py
maginator/main.py
maginator/messages.py
maginator/workflow.py
maginator/recommended_workflow/reads_to_bins.Snakefile
maginator/recommended_workflow/envs/checkm.yaml
maginator/recommended_workflow/envs/import_hg_19.R
maginator/recommended_workflow/envs/metabat2.yaml
maginator/recommended_workflow/envs/preprocess.yaml
maginator/recommended_workflow/envs/samtools.yaml
maginator/recommended_workflow/envs/vamb.yaml
maginator/test_data/clusters.tsv
maginator/test_data/contigs.fasta.gz
maginator/test_data/reads.csv
maginator/workflow/01_filter.Snakefile
maginator/workflow/02_gtdbtk.Snakefile
maginator/workflow/03_parse_gtdbtk.Snakefile
maginator/workflow/04_filter_geneclusters.Snakefile
maginator/workflow/05_gene_count_mat.Snakefile
maginator/workflow/06_prescreening_genes.Snakefile
maginator/workflow/07_signature_genes.Snakefile
maginator/workflow/08_outgroup.Snakefile
maginator/workflow/09_pileup.Snakefile
maginator/workflow/10_pileup_parse.Snakefile
maginator/workflow/11_alignment.Snakefile
maginator/workflow/12_phylo.Snakefile
maginator/workflow/13_gene_tax.Snakefile
maginator/workflow/benchmark.Snakefile
maginator/workflow/functional.Snakefile
maginator/workflow/reads_to_bins.Snakefile
maginator/workflow/signature_reads.Snakefile
maginator/workflow/envs/filter_geneclusters.yaml
maginator/workflow/envs/filter_geneclusters.yaml.BACKUP.6404.yaml
maginator/workflow/envs/filter_geneclusters.yaml.BASE.6404.yaml
maginator/workflow/envs/filter_geneclusters.yaml.LOCAL.6404.yaml
maginator/workflow/envs/filter_geneclusters.yaml.REMOTE.6404.yaml
maginator/workflow/envs/filter_gtdbtk.yaml
maginator/workflow/envs/phylo.yaml
maginator/workflow/envs/signature_genes.yaml
maginator/workflow/envs/signature_reads.yaml
maginator/workflow/scripts/Functions_v4.R
maginator/workflow/scripts/MGS_counts.R
maginator/workflow/scripts/SG_refinement.R
maginator/workflow/scripts/abundance_profiles.R
maginator/workflow/scripts/allele_frequency_mat.R
maginator-1.0.2.dist-info/licenses/LICENSE
maginator-1.0.2.dist-info/METADATA
maginator-1.0.2.dist-info/WHEEL
maginator-1.0.2.dist-info/entry_points.txt
maginator-1.0.2.dist-info/top_level.txt
maginator-1.0.2.dist-info/RECORD
