Metadata-Version: 2.4
Name: maginator
Version: 1.0.2
Summary: MAGinator: Abundance, strain, and functional profiling of MAGs
Home-page: https://github.com/Russel88/MAGinator
Author: Jakob Russel & Trine Zachariasen
Author-email: russel2620@gmail.com,trine_zachariasen@hotmail.com
Classifier: Programming Language :: Python :: 3
Classifier: License :: OSI Approved :: MIT License
Classifier: Operating System :: OS Independent
Classifier: Topic :: Scientific/Engineering :: Bio-Informatics
Classifier: Topic :: Software Development :: Libraries :: Python Modules
Classifier: Development Status :: 4 - Beta
Requires-Python: >=3.12
License-File: LICENSE
Requires-Dist: setuptools
Requires-Dist: snakemake-executor-plugin-cluster-generic
Dynamic: author
Dynamic: author-email
Dynamic: classifier
Dynamic: description
Dynamic: description-content-type
Dynamic: home-page
Dynamic: license-file
Dynamic: requires-dist
Dynamic: requires-python
Dynamic: summary
